LICENSE
MANIFEST.in
README.md
setup.cfg
setup.py
autodocumenter_test.egg-info/PKG-INFO
autodocumenter_test.egg-info/SOURCES.txt
autodocumenter_test.egg-info/dependency_links.txt
autodocumenter_test.egg-info/entry_points.txt
autodocumenter_test.egg-info/requires.txt
autodocumenter_test.egg-info/top_level.txt
src/autodocumenter/__init__.py
src/autodocumenter/__main__.py
src/autodocumenter/compile_doc/__init__.py
src/autodocumenter/compile_doc/compile_doc.py
src/autodocumenter/compile_doc/templates/base.rst
src/autodocumenter/compile_doc/templates/class.rst
src/autodocumenter/compile_doc/templates/module.rst
src/autodocumenter/compile_doc/utils/__init__.py
src/autodocumenter/compile_doc/utils/edit_config.py
src/autodocumenter/compile_doc/utils/edit_index.py
src/autodocumenter/compile_doc/utils/edit_reference.py
src/autodocumenter/compile_doc/utils/edit_user_guide.py
src/autodocumenter/generate_doc/__init__.py
src/autodocumenter/generate_doc/generate_doc.py
src/autodocumenter/generate_doc/prepare_file.py
src/autodocumenter/generate_doc/write_file.py
src/autodocumenter/generate_doc/utils/__init__.py
src/autodocumenter/generate_doc/utils/config.yaml
src/autodocumenter/generate_doc/utils/generate_response.py
src/autodocumenter/generate_doc/utils/hashing.py
src/autodocumenter/generate_doc/utils/parse_file.py
src/autodocumenter/generate_doc/utils/token_counting.py
src/autodocumenter/utils/__init__.py
src/autodocumenter/utils/constants.py
src/autodocumenter/utils/misc.py
src/autodocumenter/utils/output.py