Metadata-Version: 2.1
Name: autodocumenter-test
Version: 0.1.5
Summary: Generate docstrings using ChatGPT and generate Sphinx documentation from the project structure.
Author: Dusan Grujicic
Author-email: dusangr22@gmail.com
License: MIT
Keywords: documentation,ChatGPT,Sphinx
Requires-Python: >3.9
License-File: LICENSE
